py4fuzzy/__init__.py
py4fuzzy-0.0.0.dist-info/METADATA
py4fuzzy-0.0.0.dist-info/WHEEL
py4fuzzy-0.0.0.dist-info/top_level.txt
py4fuzzy-0.0.0.dist-info/RECORD
