Metadata-Version: 2.1
Name: py4fuzzy
Version: 0.0.0
Summary: Fuzzy Logic
Author: Harsh Gupta
Author-email: harshnkgupta@gmail.com
